robust/__init__.py
robust/alarm.py
robust/exception.py
robust/tests.py
robust/tools.py
robust/version.py
pyrobustness-1.1.2.dist-info/LICENSE
pyrobustness-1.1.2.dist-info/METADATA
pyrobustness-1.1.2.dist-info/WHEEL
pyrobustness-1.1.2.dist-info/top_level.txt
pyrobustness-1.1.2.dist-info/RECORD
