Metadata-Version: 2.1
Name: pyrobustness
Version: 1.1.2
Summary: A simple util library for creating applications which needs to keep running, despite abnormalities
Home-page: https://github.com/zaibacu/pyRobustness
Author: Šarūnas Navickas
Author-email: zaibacu@gmail.com
License: MIT
Platform: UNKNOWN
